pymysql_manager/__init__.py
pymysql_manager-0.0.2.dist-info/METADATA
pymysql_manager-0.0.2.dist-info/RECORD
pymysql_manager-0.0.2.dist-info/WHEEL
pymysql_manager-0.0.2.dist-info/top_level.txt
