Metadata-Version: 2.1
Name: pymysql-manager
Version: 0.0.2
Summary: pymysql connection & pool manager for python3
Home-page: https://github.com/zhouyl/pymysql-connection-manager
Author: zhouyl
Author-email: 81438567@qq.com
License: MIT
Keywords: mysql,pymysql,mysql-connection,mysql-pool,pool,connection-manager
Platform: UNKNOWN
Classifier: Operating System :: OS Independent
Classifier: Intended Audience :: Developers
Classifier: License :: OSI Approved :: MIT License
Classifier: Programming Language :: Python
Classifier: Programming Language :: Python :: 3.5
Classifier: Programming Language :: Python :: 3.6
Classifier: Topic :: Software Development :: Libraries :: Python Modules
Classifier: Topic :: Database :: Front-Ends
Requires-Dist: PyMySQL (>=0.8.0)
Requires-Dist: connection-pool (>=0.0.1)
